{
    "$schema":  "http://schema.management.azure.com/schemas/2015-01-01/deploymentParameters.json#",
    "contentVersion":  "1.0.0.0",
    "parameters":  {
                       "environmentTag":  {
                                              "value":  "dev"
                                          },
                       "dri":  {
                                   "value":  "admin@contoso.com"
                               },
                       "projectName":  {
                                           "value":  "adap"
                                       },
                       "chargebackId":  {
                                            "value":  "8675309"
                                        },
                       "projectVersion":  {
                                              "value":  "1.0"
                                          },
                       "userAssignedIdentityName":  {
                                                        "value":  "default"
                                                    },
                       "locationtag":  {
                                           "value":  "eus"
                                       }
                   }
}
